dynamic_indicators_tools/__init__.py
dynamic_indicators_tools/main_dynamic_indicators_process.py
dynamic_indicators_tools/differentials_systems/__init__.py
dynamic_indicators_tools/differentials_systems/data_transformations.py
dynamic_indicators_tools/differentials_systems/diff_system.py
dynamic_indicators_tools/differentials_systems/solver_integrators.py
dynamic_indicators_tools/dynamic_indicators/__init__.py
dynamic_indicators_tools/dynamic_indicators/dynamic_indicators_process.py
dynamic_indicators_tools/dynamic_indicators/dynamic_indicators_utils.py
dynamic_indicators_tools/dynamic_indicators/params_methods.py
dynamic_indicators_tools/dynamic_indicators/plot_descriptors.py
dynamic_indicators_tools/dynamic_indicators/finite_time_lyapunov_exponents/__init__.py
dynamic_indicators_tools/dynamic_indicators/finite_time_lyapunov_exponents/ftle_indicator.py
dynamic_indicators_tools/dynamic_indicators/finite_time_lyapunov_exponents/ftle_params.py
dynamic_indicators_tools/dynamic_indicators/finite_time_lyapunov_exponents/ftle_utils.py
dynamic_indicators_tools/dynamic_indicators/lagrangian_descriptors/__init__.py
dynamic_indicators_tools/dynamic_indicators/lagrangian_descriptors/ld_indicator.py
dynamic_indicators_tools/dynamic_indicators/lagrangian_descriptors/ld_integrators.py
dynamic_indicators_tools/dynamic_indicators/lagrangian_descriptors/ld_params.py
dynamic_indicators_tools/dynamic_indicators/lagrangian_descriptors/ld_utils.py
dynamic_indicators_tools/dynamic_indicators/poincare_maps/__init__.py
dynamic_indicators_tools/dynamic_indicators/poincare_maps/poincare_indicator.py
dynamic_indicators_tools/dynamic_indicators/poincare_maps/poincare_params.py
dynamic_indicators_tools/dynamic_indicators/poincare_maps/poincare_utils.py
dynamic_indicators_tools/numercial_methods/__init__.py
dynamic_indicators_tools/numercial_methods/differentiation.py
dynamic_indicators_tools/numercial_methods/integrators.py
tests/__init__.py
tests/test_data_transformations.py
dynamic_indicators_tools-2.0.0.dist-info/LICENSE
dynamic_indicators_tools-2.0.0.dist-info/METADATA
dynamic_indicators_tools-2.0.0.dist-info/WHEEL
dynamic_indicators_tools-2.0.0.dist-info/top_level.txt
dynamic_indicators_tools-2.0.0.dist-info/RECORD
