Metadata-Version: 2.1
Name: dynamic_indicators_tools
Version: 2.0.0
Summary: Repositorio que recoge herramientas para el análisis de sistemas dinámicos
Home-page: https://github.com/santhiperbolico/dynamic_indicators_tools
Author: Santiago Arranz Sanz
Classifier: Programming Language :: Python :: 3
Classifier: License :: OSI Approved :: MIT License
Classifier: Operating System :: OS Independent
Requires-Python: >=3.11
License-File: LICENSE
Requires-Dist: numpy
Requires-Dist: scipy
Requires-Dist: matplotlib
Requires-Dist: attrs
Requires-Dist: tqdm
Requires-Dist: pyqt5
